cfg_generator/CFG_Generator.py
cfg_generator/__init__.py
cfg_generator-0.0.2.dist-info/LICENSE
cfg_generator-0.0.2.dist-info/METADATA
cfg_generator-0.0.2.dist-info/WHEEL
cfg_generator-0.0.2.dist-info/top_level.txt
cfg_generator-0.0.2.dist-info/RECORD
