Metadata-Version: 2.1
Name: cfg-generator
Version: 0.0.2
Summary: A tool to be used to generate random Context-Free Grammars
Home-page: https://github.com/LallahK/CFG_Generator
Author: Abdullah Karbanee
Author-email: abdullahkarbanee@gmail.com
License: UNKNOWN
Project-URL: Bug Tracker, https://github.com/LallahK/CFG_Generator/issues
Platform: UNKNOWN
Classifier: Programming Language :: Python :: 3
Classifier: License :: OSI Approved :: MIT License
Classifier: Operating System :: OS Independent
Requires-Python: >=3.6
